src/mac_unit.sv
`timescale 1ns/1ps

module mac_unit #(
    parameter WIDTH = 16
)(
    input  logic              clk,
    input  logic              rst_n,
    input  logic              en,       // Enable: High when FIFO is not empty
    input  logic              clr,      // Clear: To reset the running total
    input  logic signed [WIDTH-1:0] a_in,
    input  logic signed [WIDTH-1:0] b_in,
    output logic signed [(WIDTH*2)-1:0] out 
);

    // Pipeline Registers
    logic signed [(WIDTH*2)-1:0] mult_reg;
    logic signed [(WIDTH*2)-1:0] acc_reg;
    logic signed [(WIDTH*2)-1:0] next_acc;

    // --- OVERFLOW DETECTION & SATURATION CONSTANTS ---
    // For a 32-bit signed accumulator
    localparam signed [31:0] MAX_POS = 32'h7FFFFFFF;
    localparam signed [31:0] MAX_NEG = 32'h80000000;

    // --- ARITHMETIC LOGIC ---
    always_comb begin
        // Preliminary addition result
        next_acc = acc_reg + mult_reg;

        // Saturation Logic:
        // If (Pos + Pos = Neg) -> Positive Overflow
        if (acc_reg > 0 && mult_reg > 0 && next_acc < 0) begin
            next_acc = MAX_POS;
        end 
        // If (Neg + Neg = Pos) -> Negative Overflow
        else if (acc_reg < 0 && mult_reg < 0 && next_acc > 0) begin
            next_acc = MAX_NEG;
        end
    end

    // --- STAGE 1: Multiplication ---
    // Latency: 1 Cycle
    always_ff @(posedge clk or negedge rst_n) begin
        if (!rst_n) begin
            mult_reg <= '0;
        end else if (en) begin
            mult_reg <= a_in * b_in;
        end
    end

    // --- STAGE 2: Accumulation with Saturation ---
    // Latency: 1 Cycle (Total 2)
    always_ff @(posedge clk or negedge rst_n) begin
        if (!rst_n) begin
            acc_reg <= '0;
        end else if (clr) begin
            acc_reg <= '0;
        end else if (en) begin
            acc_reg <= next_acc; // Store the saturated result
        end
    end

    // Direct output assignment
    assign out = acc_reg;

endmodule

src/sync_fifo.sv
`timescale 1ns/1ps

module sync_fifo #(
    parameter WIDTH = 16,
    parameter DEPTH = 8,              // Must be a power of 2
    localparam ADDR_W = $clog2(DEPTH) // Address width
)(
    input  logic              clk,
    input  logic              rst_n,

    // Write Interface
    input  logic              wr_en,
    input  logic [WIDTH-1:0]  din,
    output logic              full,

    // Read Interface
    input  logic              rd_en,
    output logic [WIDTH-1:0]  dout,
    output logic              empty
);

    // The Memory Array
    logic [WIDTH-1:0] mem [DEPTH-1:0];

    // Pointers
    logic [ADDR_W:0] wr_ptr; // One extra bit to distinguish full vs empty
    logic [ADDR_W:0] rd_ptr;

    // --- Status Logic ---
    // If pointers are identical, it's empty. 
    // If only the MSB is different, it's full.
    assign empty = (wr_ptr == rd_ptr);
    assign full  = (wr_ptr[ADDR_W] != rd_ptr[ADDR_W]) && 
                   (wr_ptr[ADDR_W-1:0] == rd_ptr[ADDR_W-1:0]);

    // --- Write Logic ---
    always_ff @(posedge clk or negedge rst_n) begin
        if (!rst_n) begin
            wr_ptr <= '0;
        end else if (wr_en && !full) begin
            mem[wr_ptr[ADDR_W-1:0]] <= din;
            wr_ptr <= wr_ptr + 1;
        end
    end

    // --- Read Logic ---
    always_ff @(posedge clk or negedge rst_n) begin
        if (!rst_n) begin
            rd_ptr <= '0;
        end else if (rd_en && !empty) begin
            dout <= mem[rd_ptr[ADDR_W-1:0]];
            rd_ptr <= rd_ptr + 1;
        end
    end

endmodule

src/top_accelerator.sv
`timescale 1ns/1ps

module top_accelerator #(
    parameter WIDTH = 16,
    parameter DEPTH = 16
)(
    input  logic              clk,
    input  logic              rst_n,

    // Input side (From Mac/Testbench)
    input  logic              wr_en,
    input  logic [WIDTH-1:0]  din_a,
    input  logic [WIDTH-1:0]  din_b,
    output logic              fifo_full,

    // Control
    input  logic              acc_clr, // Clear the MAC accumulator
    
    // Output side
    output logic signed [(WIDTH*2)-1:0] acc_out,
    output logic              valid_out
);

    // Internal Wires
    logic [WIDTH-1:0] fifo_a_out, fifo_b_out;
    logic fifo_empty;
    logic mac_en;

    // The MAC should run as long as there is data in the FIFO
    assign mac_en = !fifo_empty;

    // 1. FIFO for Operand A
    sync_fifo #(.WIDTH(WIDTH), .DEPTH(DEPTH)) fifo_a (
        .clk(clk), .rst_n(rst_n),
        .wr_en(wr_en), .din(din_a), .full(fifo_full), // Simplified: assume both FIFOs fill together
        .rd_en(mac_en), .dout(fifo_a_out), .empty(fifo_empty)
    );

    // 2. FIFO for Operand B
    sync_fifo #(.WIDTH(WIDTH), .DEPTH(DEPTH)) fifo_b (
        .clk(clk), .rst_n(rst_n),
        .wr_en(wr_en), .din(din_b), .full(), 
        .rd_en(mac_en), .dout(fifo_b_out), .empty()
    );

    // 3. The MAC Unit
    mac_unit #(.WIDTH(WIDTH)) processor (
        .clk(clk), .rst_n(rst_n),
        .en(mac_en), .clr(acc_clr),
        .a_in(fifo_a_out), .b_in(fifo_b_out),
        .out(acc_out)
    );

    // Pipeline delay for the valid signal (MAC has 2-cycle latency)
    logic [1:0] valid_pipe;
    always_ff @(posedge clk or negedge rst_n) begin
        if (!rst_n) valid_pipe <= 2'b00;
        else        valid_pipe <= {valid_pipe[0], mac_en};
    end
    assign valid_out = valid_pipe[1];

endmodule

sim/waveform_V1.0.vcd
$version Generated by VerilatedVcd $end
$timescale 1ps $end
 $scope module TOP $end
  $var wire 1 Q clk $end
  $var wire 1 R rst_n $end
  $var wire 1 S wr_en $end
  $var wire 16 T din_a [15:0] $end
  $var wire 16 U din_b [15:0] $end
  $var wire 1 V fifo_full $end
  $var wire 1 W acc_clr $end
  $var wire 32 X acc_out [31:0] $end
  $var wire 1 Y valid_out $end
  $scope module top_accelerator $end
   $var wire 32 Z WIDTH [31:0] $end
   $var wire 32 Z DEPTH [31:0] $end
   $var wire 1 Q clk $end
   $var wire 1 R rst_n $end
   $var wire 1 S wr_en $end
   $var wire 16 T din_a [15:0] $end
   $var wire 16 U din_b [15:0] $end
   $var wire 1 V fifo_full $end
   $var wire 1 W acc_clr $end
   $var wire 32 X acc_out [31:0] $end
   $var wire 1 Y valid_out $end
   $var wire 16 # fifo_a_out [15:0] $end
   $var wire 16 $ fifo_b_out [15:0] $end
   $var wire 1 % fifo_empty $end
   $var wire 1 & mac_en $end
   $var wire 2 ' valid_pipe [1:0] $end
   $scope module fifo_a $end
    $var wire 32 Z WIDTH [31:0] $end
    $var wire 32 Z DEPTH [31:0] $end
    $var wire 32 [ ADDR_W [31:0] $end
    $var wire 1 Q clk $end
    $var wire 1 R rst_n $end
    $var wire 1 S wr_en $end
    $var wire 16 T din [15:0] $end
    $var wire 1 V full $end
    $var wire 1 & rd_en $end
    $var wire 16 # dout [15:0] $end
    $var wire 1 % empty $end
    $var wire 16 ( mem[0] [15:0] $end
    $var wire 16 ) mem[1] [15:0] $end
    $var wire 16 * mem[2] [15:0] $end
    $var wire 16 + mem[3] [15:0] $end
    $var wire 16 , mem[4] [15:0] $end
    $var wire 16 - mem[5] [15:0] $end
    $var wire 16 . mem[6] [15:0] $end
    $var wire 16 / mem[7] [15:0] $end
    $var wire 16 0 mem[8] [15:0] $end
    $var wire 16 1 mem[9] [15:0] $end
    $var wire 16 2 mem[10] [15:0] $end
    $var wire 16 3 mem[11] [15:0] $end
    $var wire 16 4 mem[12] [15:0] $end
    $var wire 16 5 mem[13] [15:0] $end
    $var wire 16 6 mem[14] [15:0] $end
    $var wire 16 7 mem[15] [15:0] $end
    $var wire 5 8 wr_ptr [4:0] $end
    $var wire 5 9 rd_ptr [4:0] $end
   $upscope $end
   $scope module fifo_b $end
    $var wire 32 Z WIDTH [31:0] $end
    $var wire 32 Z DEPTH [31:0] $end
    $var wire 32 [ ADDR_W [31:0] $end
    $var wire 1 Q clk $end
    $var wire 1 R rst_n $end
    $var wire 1 S wr_en $end
    $var wire 16 U din [15:0] $end
    $var wire 1 : full $end
    $var wire 1 & rd_en $end
    $var wire 16 $ dout [15:0] $end
    $var wire 1 ; empty $end
    $var wire 16 < mem[0] [15:0] $end
    $var wire 16 = mem[1] [15:0] $end
    $var wire 16 > mem[2] [15:0] $end
    $var wire 16 ? mem[3] [15:0] $end
    $var wire 16 @ mem[4] [15:0] $end
    $var wire 16 A mem[5] [15:0] $end
    $var wire 16 B mem[6] [15:0] $end
    $var wire 16 C mem[7] [15:0] $end
    $var wire 16 D mem[8] [15:0] $end
    $var wire 16 E mem[9] [15:0] $end
    $var wire 16 F mem[10] [15:0] $end
    $var wire 16 G mem[11] [15:0] $end
    $var wire 16 H mem[12] [15:0] $end
    $var wire 16 I mem[13] [15:0] $end
    $var wire 16 J mem[14] [15:0] $end
    $var wire 16 K mem[15] [15:0] $end
    $var wire 5 L wr_ptr [4:0] $end
    $var wire 5 M rd_ptr [4:0] $end
   $upscope $end
   $scope module processor $end
    $var wire 32 Z WIDTH [31:0] $end
    $var wire 1 Q clk $end
    $var wire 1 R rst_n $end
    $var wire 1 & en $end
    $var wire 1 W clr $end
    $var wire 16 # a_in [15:0] $end
    $var wire 16 $ b_in [15:0] $end
    $var wire 32 X out [31:0] $end
    $var wire 32 N mult_reg [31:0] $end
    $var wire 32 O acc_reg [31:0] $end
    $var wire 32 P next_acc [31:0] $end
    $var wire 32 \ MAX_POS [31:0] $end
    $var wire 32 ] MAX_NEG [31:0] $end
   $upscope $end
  $upscope $end
 $upscope $end
$enddefinitions $end


#0
b0000000000000000 #
b0000000000000000 $
1%
0&
b00 '
b0000000000000000 (
b0000000000000000 )
b0000000000000000 *
b0000000000000000 +
b0000000000000000 ,
b0000000000000000 -
b0000000000000000 .
b0000000000000000 /
b0000000000000000 0
b0000000000000000 1
b0000000000000000 2
b0000000000000000 3
b0000000000000000 4
b0000000000000000 5
b0000000000000000 6
b0000000000000000 7
b00000 8
b00000 9
0:
1;
b0000000000000000 <
b0000000000000000 =
b0000000000000000 >
b0000000000000000 ?
b0000000000000000 @
b0000000000000000 A
b0000000000000000 B
b0000000000000000 C
b0000000000000000 D
b0000000000000000 E
b0000000000000000 F
b0000000000000000 G
b0000000000000000 H
b0000000000000000 I
b0000000000000000 J
b0000000000000000 K
b00000 L
b00000 M
b00000000000000000000000000000000 N
b00000000000000000000000000000000 O
b00000000000000000000000000000000 P
0Q
0R
0S
b0000000000000000 T
b0000000000000000 U
0V
1W
b00000000000000000000000000000000 X
0Y
b00000000000000000000000000010000 Z
b00000000000000000000000000000100 [
b01111111111111111111111111111111 \
b10000000000000000000000000000000 ]
#1
1Q
#2
0Q
1R
0W
#3
1Q
#4
0Q
1S
b0000000000001010 T
b0000000000000010 U
#5
0%
1&
b0000000000001010 (
b00001 8
0;
b0000000000000010 <
b00001 L
1Q
#6
0Q
b0000000000010100 T
b0000000000000011 U
#7
b0000000000001010 #
b0000000000000010 $
b01 '
b0000000000010100 )
b00010 8
b00001 9
b0000000000000011 =
b00010 L
b00001 M
1Q
#8
0Q
b0000000000011110 T
b0000000000000100 U
#9
b0000000000010100 #
b0000000000000011 $
b11 '
b0000000000011110 *
b00011 8
b00010 9
b0000000000000100 >
b00011 L
b00010 M
b00000000000000000000000000010100 N
b00000000000000000000000000010100 P
1Q
1Y
#10
0Q
b0000000000101000 T
b0000000000000101 U
#11
b0000000000011110 #
b0000000000000100 $
b0000000000101000 +
b00100 8
b00011 9
b0000000000000101 ?
b00100 L
b00011 M
b00000000000000000000000000111100 N
b00000000000000000000000000010100 O
b00000000000000000000000001010000 P
1Q
b00000000000000000000000000010100 X
#12
0Q
b0000000000110010 T
b0000000000000110 U
#13
b0000000000101000 #
b0000000000000101 $
b0000000000110010 ,
b00101 8
b00100 9
b0000000000000110 @
b00101 L
b00100 M
b00000000000000000000000001111000 N
b00000000000000000000000001010000 O
b00000000000000000000000011001000 P
1Q
b00000000000000000000000001010000 X
#14
0Q
0S
#15
b0000000000110010 #
b0000000000000110 $
1%
0&
b00101 9
1;
b00101 M
b00000000000000000000000011001000 N
b00000000000000000000000011001000 O
b00000000000000000000000110010000 P
1Q
b00000000000000000000000011001000 X
#16
0Q
#17
b10 '
1Q
#18
0Q
#19
b00 '
1Q
0Y
