src/mac_unit.sv
`timescale 1ns/1ps

module mac_unit #(
    parameter IN_WIDTH  = 8,
    parameter ACC_WIDTH = 32
)(
    input  logic              clk,
    input  logic              rst_n,
    input  logic              en,       // Pipeline clock enable (freeze control)
    input  logic              clr,      // Synchronous accumulator clear
    input  logic signed [IN_WIDTH-1:0]  a_in,  // INT8 Activation
    input  logic signed [IN_WIDTH-1:0]  b_in,  // INT8 Weight
    output logic signed [ACC_WIDTH-1:0] out    // INT32 Accumulated Output
);

    // Pipeline Stage Registers
    // Multiplying two 8-bit signed numbers requires a 16-bit intermediate container
    logic signed [(IN_WIDTH*2)-1:0] mult_reg; 
    logic signed [ACC_WIDTH-1:0]    acc_reg;
    logic signed [ACC_WIDTH-1:0]    next_acc;

    // --- 32-BIT SIGNED SATURATION CONSTANTS ---
    localparam signed [ACC_WIDTH-1:0] MAX_POS = 32'h7FFFFFFF;
    localparam signed [ACC_WIDTH-1:0] MAX_NEG = 32'h80000000;

    // --- ARITHMETIC LOGIC (INT32 Accumulation with Saturation) ---
    always_comb begin
        // Automatically sign-extend the 16-bit multiplication product up to 32 bits before adding
        next_acc = acc_reg + signed'(mult_reg);

        // Positive Overflow Safeguard: If (Pos + Pos = Neg) -> Snap to Max Positive
        if (acc_reg > 0 && mult_reg > 0 && next_acc < 0) begin
            next_acc = MAX_POS;
        end 
        // Negative Overflow Safeguard: If (Neg + Neg = Pos) -> Snap to Max Negative
        else if (acc_reg < 0 && mult_reg < 0 && next_acc > 0) begin
            next_acc = MAX_NEG;
        end
    end

    // --- STAGE 1: INT8 Signed Multiplication ---
    always_ff @(posedge clk or negedge rst_n) begin
        if (!rst_n) begin
            mult_reg <= '0;
        end else if (en) begin
            mult_reg <= a_in * b_in;
        end
    end

    // --- STAGE 2: INT32 Accumulation with Freeze Control ---
    always_ff @(posedge clk or negedge rst_n) begin
        if (!rst_n) begin
            acc_reg <= '0;
        end else if (clr) begin
            acc_reg <= '0;
        end else if (en) begin
            acc_reg <= next_acc;
        end
    end

    // Continuous drive out to output port
    assign out = acc_reg;

endmodule

src/sync_fifo.sv
`timescale 1ns/1ps

module sync_fifo #(
    parameter WIDTH = 16,
    parameter DEPTH = 8,              // Must be a power of 2
    localparam ADDR_W = $clog2(DEPTH) // Address width
)(
    input  logic              clk,
    input  logic              rst_n,

    // Write Interface
    input  logic              wr_en,
    input  logic [WIDTH-1:0]  din,
    output logic              full,

    // Read Interface
    input  logic              rd_en,
    output logic [WIDTH-1:0]  dout,
    output logic              empty
);

    // The Memory Array
    logic [WIDTH-1:0] mem [DEPTH-1:0];

    // Pointers
    logic [ADDR_W:0] wr_ptr; // One extra bit to distinguish full vs empty
    logic [ADDR_W:0] rd_ptr;

    // --- Status Logic ---
    // If pointers are identical, it's empty. 
    // If only the MSB is different, it's full.
    assign empty = (wr_ptr == rd_ptr);
    assign full  = (wr_ptr[ADDR_W] != rd_ptr[ADDR_W]) && 
                   (wr_ptr[ADDR_W-1:0] == rd_ptr[ADDR_W-1:0]);

    // --- Write Logic ---
    always_ff @(posedge clk or negedge rst_n) begin
        if (!rst_n) begin
            wr_ptr <= '0;
        end else if (wr_en && !full) begin
            mem[wr_ptr[ADDR_W-1:0]] <= din;
            wr_ptr <= wr_ptr + 1;
        end
    end

    // --- Read Logic ---
    always_ff @(posedge clk or negedge rst_n) begin
        if (!rst_n) begin
            rd_ptr <= '0;
        end else if (rd_en && !empty) begin
            dout <= mem[rd_ptr[ADDR_W-1:0]];
            rd_ptr <= rd_ptr + 1;
        end
    end

endmodule

src/top_accelerator.sv
`timescale 1ns/1ps

module top_accelerator #(
    parameter LANES     = 4,
    parameter IN_WIDTH  = 8,
    parameter ACC_WIDTH = 32,
    parameter DEPTH     = 16
)(
    input  logic              clk,
    input  logic              rst_n,

    // --- Host Control Interfaces ---
    input  logic              acc_clr,     // Synchronously clears running totals across all lanes
    input  logic              pipeline_en, // Global execution stall control (1=Run, 0=Stall)

    // --- Upstream Streaming Interface (Valid/Ready Handshake) ---
    input  logic              v_in,        // Upstream data payload is valid
    output logic              r_ready,     // Accelerator is ready to accept data
    input  logic signed [(LANES*IN_WIDTH)-1:0] vec_din_a, // Packed 32-bit Vector A input (4x INT8)
    input  logic signed [(LANES*IN_WIDTH)-1:0] vec_din_b, // Packed 32-bit Vector B input (4x INT8)

    // --- Downstream Output Interface (Valid Flag) ---
    output logic              v_out,       // Downstream calculation output is valid
    output logic signed [(LANES*ACC_WIDTH)-1:0] vec_acc_out // Packed 128-bit Vector Output (4x INT32)
);

    // Internal Control Matrix Wires
    logic [LANES-1:0] lane_fifo_empty;
    logic [LANES-1:0] lane_fifo_full;
    logic             all_fifos_have_data;
    logic             mac_exec_en;
    
    // Unpacked internal vectors for routing to/from lanes
    logic signed [IN_WIDTH-1:0]   fifo_a_out [LANES-1:0];
    logic signed [IN_WIDTH-1:0]   fifo_b_out [LANES-1:0];
    logic signed [ACC_WIDTH-1:0]  lane_out   [LANES-1:0];

    // --- Dynamic Flow Control & Backpressure Logic ---
    // The accelerator accepts incoming writes ONLY if none of the internal lane FIFOs are full
    assign r_ready = !( |lane_fifo_full );

    // Core execution steps forward ONLY if there is valid data in all queues and the host hasn't stalled the pipeline
    assign all_fifos_have_data = !( |lane_fifo_empty );
    assign mac_exec_en         = all_fifos_have_data && pipeline_en;

    // --- Structural SIMD Lane Generation Block ---
    genvar i;
    generate
        for (i = 0; i < LANES; i++) begin : simd_lanes
            
            // Dedicated INT8 Input Queue for Operand A Component
            sync_fifo #(.WIDTH(IN_WIDTH), .DEPTH(DEPTH)) fifo_a_inst (
                .clk(clk), .rst_n(rst_n),
                .wr_en(v_in && r_ready), 
                .din(vec_din_a[(i+1)*IN_WIDTH-1 : i*IN_WIDTH]),
                .full(lane_fifo_full[i]),
                .rd_en(mac_exec_en), 
                .dout(fifo_a_out[i]), 
                .empty(lane_fifo_empty[i])
            );

            // Dedicated INT8 Input Queue for Operand B Component
            sync_fifo #(.WIDTH(IN_WIDTH), .DEPTH(DEPTH)) fifo_b_inst (
                .clk(clk), .rst_n(rst_n),
                .wr_en(v_in && r_ready), 
                .din(vec_din_b[(i+1)*IN_WIDTH-1 : i*IN_WIDTH]),
                .full(), // Throttling is globally governed by the unified lane array flags
                .rd_en(mac_exec_en), 
                .dout(fifo_b_out[i]), 
                .empty()
            );

            // Hybrid INT8/INT32 Computing Core
            mac_unit #(
                .IN_WIDTH(IN_WIDTH), 
                .ACC_WIDTH(ACC_WIDTH)
            ) mac_core (
                .clk(clk), .rst_n(rst_n),
                .en(mac_exec_en), .clr(acc_clr),
                .a_in(fifo_a_out[i]), .b_in(fifo_b_out[i]),
                .out(lane_out[i])
            );

            // Pack parallel internal array channels back out onto the wide vector bus
            assign vec_acc_out[(i+1)*ACC_WIDTH-1 : i*ACC_WIDTH] = lane_out[i];
        end
    endgenerate

    // --- Control-Path Valid Delay Pipeline ---
    logic [2:0] valid_pipe;
    always_ff @(posedge clk or negedge rst_n) begin
        if (!rst_n) begin
            valid_pipe <= 2'b00;
        end else if (pipeline_en) begin
            // Shift validity flag down the pipeline only if the engine isn't actively stalled
            valid_pipe <= {valid_pipe[0], mac_exec_en};
        end
    end
    
    // Assign downstream valid flag based on the 2-cycle execution latency
    assign v_out = valid_pipe[2];

endmodule

sim/waveform.vcd
$version Generated by VerilatedVcd $end
$timescale 1ps $end
 $scope module TOP $end
  $var wire 1 +" clk $end
  $var wire 1 ," rst_n $end
  $var wire 1 -" acc_clr $end
  $var wire 1 ." pipeline_en $end
  $var wire 1 /" v_in $end
  $var wire 1 0" r_ready $end
  $var wire 32 1" vec_din_a [31:0] $end
  $var wire 32 2" vec_din_b [31:0] $end
  $var wire 1 3" v_out $end
  $var wire 128 4" vec_acc_out [127:0] $end
  $scope module top_accelerator $end
   $var wire 32 B" LANES [31:0] $end
   $var wire 32 C" IN_WIDTH [31:0] $end
   $var wire 32 D" ACC_WIDTH [31:0] $end
   $var wire 32 E" DEPTH [31:0] $end
   $var wire 1 +" clk $end
   $var wire 1 ," rst_n $end
   $var wire 1 -" acc_clr $end
   $var wire 1 ." pipeline_en $end
   $var wire 1 /" v_in $end
   $var wire 1 0" r_ready $end
   $var wire 32 1" vec_din_a [31:0] $end
   $var wire 32 2" vec_din_b [31:0] $end
   $var wire 1 3" v_out $end
   $var wire 128 4" vec_acc_out [127:0] $end
   $var wire 4 # lane_fifo_empty [3:0] $end
   $var wire 4 $ lane_fifo_full [3:0] $end
   $var wire 1 % all_fifos_have_data $end
   $var wire 1 8" mac_exec_en $end
   $var wire 8 & fifo_a_out[0] [7:0] $end
   $var wire 8 ' fifo_a_out[1] [7:0] $end
   $var wire 8 ( fifo_a_out[2] [7:0] $end
   $var wire 8 ) fifo_a_out[3] [7:0] $end
   $var wire 8 * fifo_b_out[0] [7:0] $end
   $var wire 8 + fifo_b_out[1] [7:0] $end
   $var wire 8 , fifo_b_out[2] [7:0] $end
   $var wire 8 - fifo_b_out[3] [7:0] $end
   $var wire 32 . lane_out[0] [31:0] $end
   $var wire 32 / lane_out[1] [31:0] $end
   $var wire 32 0 lane_out[2] [31:0] $end
   $var wire 32 1 lane_out[3] [31:0] $end
   $var wire 3 2 valid_pipe [2:0] $end
   $scope module simd_lanes[0] $end
    $scope module fifo_a_inst $end
     $var wire 32 C" WIDTH [31:0] $end
     $var wire 32 E" DEPTH [31:0] $end
     $var wire 32 B" ADDR_W [31:0] $end
     $var wire 1 +" clk $end
     $var wire 1 ," rst_n $end
     $var wire 1 9" wr_en $end
     $var wire 8 :" din [7:0] $end
     $var wire 1 3 full $end
     $var wire 1 8" rd_en $end
     $var wire 8 4 dout [7:0] $end
     $var wire 1 5 empty $end
     $var wire 8 6 mem[0] [7:0] $end
     $var wire 8 7 mem[1] [7:0] $end
     $var wire 8 8 mem[2] [7:0] $end
     $var wire 8 9 mem[3] [7:0] $end
     $var wire 8 : mem[4] [7:0] $end
     $var wire 8 ; mem[5] [7:0] $end
     $var wire 8 < mem[6] [7:0] $end
     $var wire 8 = mem[7] [7:0] $end
     $var wire 8 > mem[8] [7:0] $end
     $var wire 8 ? mem[9] [7:0] $end
     $var wire 8 @ mem[10] [7:0] $end
     $var wire 8 A mem[11] [7:0] $end
     $var wire 8 B mem[12] [7:0] $end
     $var wire 8 C mem[13] [7:0] $end
     $var wire 8 D mem[14] [7:0] $end
     $var wire 8 E mem[15] [7:0] $end
     $var wire 5 F wr_ptr [4:0] $end
     $var wire 5 G rd_ptr [4:0] $end
    $upscope $end
    $scope module fifo_b_inst $end
     $var wire 32 C" WIDTH [31:0] $end
     $var wire 32 E" DEPTH [31:0] $end
     $var wire 32 B" ADDR_W [31:0] $end
     $var wire 1 +" clk $end
     $var wire 1 ," rst_n $end
     $var wire 1 9" wr_en $end
     $var wire 8 ;" din [7:0] $end
     $var wire 1 H full $end
     $var wire 1 8" rd_en $end
     $var wire 8 I dout [7:0] $end
     $var wire 1 J empty $end
     $var wire 8 K mem[0] [7:0] $end
     $var wire 8 L mem[1] [7:0] $end
     $var wire 8 M mem[2] [7:0] $end
     $var wire 8 N mem[3] [7:0] $end
     $var wire 8 O mem[4] [7:0] $end
     $var wire 8 P mem[5] [7:0] $end
     $var wire 8 Q mem[6] [7:0] $end
     $var wire 8 R mem[7] [7:0] $end
     $var wire 8 S mem[8] [7:0] $end
     $var wire 8 T mem[9] [7:0] $end
     $var wire 8 U mem[10] [7:0] $end
     $var wire 8 V mem[11] [7:0] $end
     $var wire 8 W mem[12] [7:0] $end
     $var wire 8 X mem[13] [7:0] $end
     $var wire 8 Y mem[14] [7:0] $end
     $var wire 8 Z mem[15] [7:0] $end
     $var wire 5 [ wr_ptr [4:0] $end
     $var wire 5 \ rd_ptr [4:0] $end
    $upscope $end
    $scope module mac_core $end
     $var wire 32 C" IN_WIDTH [31:0] $end
     $var wire 32 D" ACC_WIDTH [31:0] $end
     $var wire 1 +" clk $end
     $var wire 1 ," rst_n $end
     $var wire 1 8" en $end
     $var wire 1 -" clr $end
     $var wire 8 4 a_in [7:0] $end
     $var wire 8 I b_in [7:0] $end
     $var wire 32 ] out [31:0] $end
     $var wire 16 ^ mult_reg [15:0] $end
     $var wire 32 ] acc_reg [31:0] $end
     $var wire 32 _ next_acc [31:0] $end
     $var wire 32 F" MAX_POS [31:0] $end
     $var wire 32 G" MAX_NEG [31:0] $end
    $upscope $end
   $upscope $end
   $scope module simd_lanes[1] $end
    $scope module fifo_a_inst $end
     $var wire 32 C" WIDTH [31:0] $end
     $var wire 32 E" DEPTH [31:0] $end
     $var wire 32 B" ADDR_W [31:0] $end
     $var wire 1 +" clk $end
     $var wire 1 ," rst_n $end
     $var wire 1 9" wr_en $end
     $var wire 8 <" din [7:0] $end
     $var wire 1 ` full $end
     $var wire 1 8" rd_en $end
     $var wire 8 a dout [7:0] $end
     $var wire 1 b empty $end
     $var wire 8 c mem[0] [7:0] $end
     $var wire 8 d mem[1] [7:0] $end
     $var wire 8 e mem[2] [7:0] $end
     $var wire 8 f mem[3] [7:0] $end
     $var wire 8 g mem[4] [7:0] $end
     $var wire 8 h mem[5] [7:0] $end
     $var wire 8 i mem[6] [7:0] $end
     $var wire 8 j mem[7] [7:0] $end
     $var wire 8 k mem[8] [7:0] $end
     $var wire 8 l mem[9] [7:0] $end
     $var wire 8 m mem[10] [7:0] $end
     $var wire 8 n mem[11] [7:0] $end
     $var wire 8 o mem[12] [7:0] $end
     $var wire 8 p mem[13] [7:0] $end
     $var wire 8 q mem[14] [7:0] $end
     $var wire 8 r mem[15] [7:0] $end
     $var wire 5 s wr_ptr [4:0] $end
     $var wire 5 t rd_ptr [4:0] $end
    $upscope $end
    $scope module fifo_b_inst $end
     $var wire 32 C" WIDTH [31:0] $end
     $var wire 32 E" DEPTH [31:0] $end
     $var wire 32 B" ADDR_W [31:0] $end
     $var wire 1 +" clk $end
     $var wire 1 ," rst_n $end
     $var wire 1 9" wr_en $end
     $var wire 8 =" din [7:0] $end
     $var wire 1 u full $end
     $var wire 1 8" rd_en $end
     $var wire 8 v dout [7:0] $end
     $var wire 1 w empty $end
     $var wire 8 x mem[0] [7:0] $end
     $var wire 8 y mem[1] [7:0] $end
     $var wire 8 z mem[2] [7:0] $end
     $var wire 8 { mem[3] [7:0] $end
     $var wire 8 | mem[4] [7:0] $end
     $var wire 8 } mem[5] [7:0] $end
     $var wire 8 ~ mem[6] [7:0] $end
     $var wire 8 !! mem[7] [7:0] $end
     $var wire 8 "! mem[8] [7:0] $end
     $var wire 8 #! mem[9] [7:0] $end
     $var wire 8 $! mem[10] [7:0] $end
     $var wire 8 %! mem[11] [7:0] $end
     $var wire 8 &! mem[12] [7:0] $end
     $var wire 8 '! mem[13] [7:0] $end
     $var wire 8 (! mem[14] [7:0] $end
     $var wire 8 )! mem[15] [7:0] $end
     $var wire 5 *! wr_ptr [4:0] $end
     $var wire 5 +! rd_ptr [4:0] $end
    $upscope $end
    $scope module mac_core $end
     $var wire 32 C" IN_WIDTH [31:0] $end
     $var wire 32 D" ACC_WIDTH [31:0] $end
     $var wire 1 +" clk $end
     $var wire 1 ," rst_n $end
     $var wire 1 8" en $end
     $var wire 1 -" clr $end
     $var wire 8 a a_in [7:0] $end
     $var wire 8 v b_in [7:0] $end
     $var wire 32 ,! out [31:0] $end
     $var wire 16 -! mult_reg [15:0] $end
     $var wire 32 ,! acc_reg [31:0] $end
     $var wire 32 .! next_acc [31:0] $end
     $var wire 32 F" MAX_POS [31:0] $end
     $var wire 32 G" MAX_NEG [31:0] $end
    $upscope $end
   $upscope $end
   $scope module simd_lanes[2] $end
    $scope module fifo_a_inst $end
     $var wire 32 C" WIDTH [31:0] $end
     $var wire 32 E" DEPTH [31:0] $end
     $var wire 32 B" ADDR_W [31:0] $end
     $var wire 1 +" clk $end
     $var wire 1 ," rst_n $end
     $var wire 1 9" wr_en $end
     $var wire 8 >" din [7:0] $end
     $var wire 1 /! full $end
     $var wire 1 8" rd_en $end
     $var wire 8 0! dout [7:0] $end
     $var wire 1 1! empty $end
     $var wire 8 2! mem[0] [7:0] $end
     $var wire 8 3! mem[1] [7:0] $end
     $var wire 8 4! mem[2] [7:0] $end
     $var wire 8 5! mem[3] [7:0] $end
     $var wire 8 6! mem[4] [7:0] $end
     $var wire 8 7! mem[5] [7:0] $end
     $var wire 8 8! mem[6] [7:0] $end
     $var wire 8 9! mem[7] [7:0] $end
     $var wire 8 :! mem[8] [7:0] $end
     $var wire 8 ;! mem[9] [7:0] $end
     $var wire 8 <! mem[10] [7:0] $end
     $var wire 8 =! mem[11] [7:0] $end
     $var wire 8 >! mem[12] [7:0] $end
     $var wire 8 ?! mem[13] [7:0] $end
     $var wire 8 @! mem[14] [7:0] $end
     $var wire 8 A! mem[15] [7:0] $end
     $var wire 5 B! wr_ptr [4:0] $end
     $var wire 5 C! rd_ptr [4:0] $end
    $upscope $end
    $scope module fifo_b_inst $end
     $var wire 32 C" WIDTH [31:0] $end
     $var wire 32 E" DEPTH [31:0] $end
     $var wire 32 B" ADDR_W [31:0] $end
     $var wire 1 +" clk $end
     $var wire 1 ," rst_n $end
     $var wire 1 9" wr_en $end
     $var wire 8 ?" din [7:0] $end
     $var wire 1 D! full $end
     $var wire 1 8" rd_en $end
     $var wire 8 E! dout [7:0] $end
     $var wire 1 F! empty $end
     $var wire 8 G! mem[0] [7:0] $end
     $var wire 8 H! mem[1] [7:0] $end
     $var wire 8 I! mem[2] [7:0] $end
     $var wire 8 J! mem[3] [7:0] $end
     $var wire 8 K! mem[4] [7:0] $end
     $var wire 8 L! mem[5] [7:0] $end
     $var wire 8 M! mem[6] [7:0] $end
     $var wire 8 N! mem[7] [7:0] $end
     $var wire 8 O! mem[8] [7:0] $end
     $var wire 8 P! mem[9] [7:0] $end
     $var wire 8 Q! mem[10] [7:0] $end
     $var wire 8 R! mem[11] [7:0] $end
     $var wire 8 S! mem[12] [7:0] $end
     $var wire 8 T! mem[13] [7:0] $end
     $var wire 8 U! mem[14] [7:0] $end
     $var wire 8 V! mem[15] [7:0] $end
     $var wire 5 W! wr_ptr [4:0] $end
     $var wire 5 X! rd_ptr [4:0] $end
    $upscope $end
    $scope module mac_core $end
     $var wire 32 C" IN_WIDTH [31:0] $end
     $var wire 32 D" ACC_WIDTH [31:0] $end
     $var wire 1 +" clk $end
     $var wire 1 ," rst_n $end
     $var wire 1 8" en $end
     $var wire 1 -" clr $end
     $var wire 8 0! a_in [7:0] $end
     $var wire 8 E! b_in [7:0] $end
     $var wire 32 Y! out [31:0] $end
     $var wire 16 Z! mult_reg [15:0] $end
     $var wire 32 Y! acc_reg [31:0] $end
     $var wire 32 [! next_acc [31:0] $end
     $var wire 32 F" MAX_POS [31:0] $end
     $var wire 32 G" MAX_NEG [31:0] $end
    $upscope $end
   $upscope $end
   $scope module simd_lanes[3] $end
    $scope module fifo_a_inst $end
     $var wire 32 C" WIDTH [31:0] $end
     $var wire 32 E" DEPTH [31:0] $end
     $var wire 32 B" ADDR_W [31:0] $end
     $var wire 1 +" clk $end
     $var wire 1 ," rst_n $end
     $var wire 1 9" wr_en $end
     $var wire 8 @" din [7:0] $end
     $var wire 1 \! full $end
     $var wire 1 8" rd_en $end
     $var wire 8 ]! dout [7:0] $end
     $var wire 1 ^! empty $end
     $var wire 8 _! mem[0] [7:0] $end
     $var wire 8 `! mem[1] [7:0] $end
     $var wire 8 a! mem[2] [7:0] $end
     $var wire 8 b! mem[3] [7:0] $end
     $var wire 8 c! mem[4] [7:0] $end
     $var wire 8 d! mem[5] [7:0] $end
     $var wire 8 e! mem[6] [7:0] $end
     $var wire 8 f! mem[7] [7:0] $end
     $var wire 8 g! mem[8] [7:0] $end
     $var wire 8 h! mem[9] [7:0] $end
     $var wire 8 i! mem[10] [7:0] $end
     $var wire 8 j! mem[11] [7:0] $end
     $var wire 8 k! mem[12] [7:0] $end
     $var wire 8 l! mem[13] [7:0] $end
     $var wire 8 m! mem[14] [7:0] $end
     $var wire 8 n! mem[15] [7:0] $end
     $var wire 5 o! wr_ptr [4:0] $end
     $var wire 5 p! rd_ptr [4:0] $end
    $upscope $end
    $scope module fifo_b_inst $end
     $var wire 32 C" WIDTH [31:0] $end
     $var wire 32 E" DEPTH [31:0] $end
     $var wire 32 B" ADDR_W [31:0] $end
     $var wire 1 +" clk $end
     $var wire 1 ," rst_n $end
     $var wire 1 9" wr_en $end
     $var wire 8 A" din [7:0] $end
     $var wire 1 q! full $end
     $var wire 1 8" rd_en $end
     $var wire 8 r! dout [7:0] $end
     $var wire 1 s! empty $end
     $var wire 8 t! mem[0] [7:0] $end
     $var wire 8 u! mem[1] [7:0] $end
     $var wire 8 v! mem[2] [7:0] $end
     $var wire 8 w! mem[3] [7:0] $end
     $var wire 8 x! mem[4] [7:0] $end
     $var wire 8 y! mem[5] [7:0] $end
     $var wire 8 z! mem[6] [7:0] $end
     $var wire 8 {! mem[7] [7:0] $end
     $var wire 8 |! mem[8] [7:0] $end
     $var wire 8 }! mem[9] [7:0] $end
     $var wire 8 ~! mem[10] [7:0] $end
     $var wire 8 !" mem[11] [7:0] $end
     $var wire 8 "" mem[12] [7:0] $end
     $var wire 8 #" mem[13] [7:0] $end
     $var wire 8 $" mem[14] [7:0] $end
     $var wire 8 %" mem[15] [7:0] $end
     $var wire 5 &" wr_ptr [4:0] $end
     $var wire 5 '" rd_ptr [4:0] $end
    $upscope $end
    $scope module mac_core $end
     $var wire 32 C" IN_WIDTH [31:0] $end
     $var wire 32 D" ACC_WIDTH [31:0] $end
     $var wire 1 +" clk $end
     $var wire 1 ," rst_n $end
     $var wire 1 8" en $end
     $var wire 1 -" clr $end
     $var wire 8 ]! a_in [7:0] $end
     $var wire 8 r! b_in [7:0] $end
     $var wire 32 (" out [31:0] $end
     $var wire 16 )" mult_reg [15:0] $end
     $var wire 32 (" acc_reg [31:0] $end
     $var wire 32 *" next_acc [31:0] $end
     $var wire 32 F" MAX_POS [31:0] $end
     $var wire 32 G" MAX_NEG [31:0] $end
    $upscope $end
   $upscope $end
  $upscope $end
 $upscope $end
$enddefinitions $end


#0
b1111 #
b0000 $
0%
b00000000 &
b00000000 '
b00000000 (
b00000000 )
b00000000 *
b00000000 +
b00000000 ,
b00000000 -
b00000000000000000000000000000000 .
b00000000000000000000000000000000 /
b00000000000000000000000000000000 0
b00000000000000000000000000000000 1
b000 2
03
b00000000 4
15
b00000000 6
b00000000 7
b00000000 8
b00000000 9
b00000000 :
b00000000 ;
b00000000 <
b00000000 =
b00000000 >
b00000000 ?
b00000000 @
b00000000 A
b00000000 B
b00000000 C
b00000000 D
b00000000 E
b00000 F
b00000 G
0H
b00000000 I
1J
b00000000 K
b00000000 L
b00000000 M
b00000000 N
b00000000 O
b00000000 P
b00000000 Q
b00000000 R
b00000000 S
b00000000 T
b00000000 U
b00000000 V
b00000000 W
b00000000 X
b00000000 Y
b00000000 Z
b00000 [
b00000 \
b00000000000000000000000000000000 ]
b0000000000000000 ^
b00000000000000000000000000000000 _
0`
b00000000 a
1b
b00000000 c
b00000000 d
b00000000 e
b00000000 f
b00000000 g
b00000000 h
b00000000 i
b00000000 j
b00000000 k
b00000000 l
b00000000 m
b00000000 n
b00000000 o
b00000000 p
b00000000 q
b00000000 r
b00000 s
b00000 t
0u
b00000000 v
1w
b00000000 x
b00000000 y
b00000000 z
b00000000 {
b00000000 |
b00000000 }
b00000000 ~
b00000000 !!
b00000000 "!
b00000000 #!
b00000000 $!
b00000000 %!
b00000000 &!
b00000000 '!
b00000000 (!
b00000000 )!
b00000 *!
b00000 +!
b00000000000000000000000000000000 ,!
b0000000000000000 -!
b00000000000000000000000000000000 .!
0/!
b00000000 0!
11!
b00000000 2!
b00000000 3!
b00000000 4!
b00000000 5!
b00000000 6!
b00000000 7!
b00000000 8!
b00000000 9!
b00000000 :!
b00000000 ;!
b00000000 <!
b00000000 =!
b00000000 >!
b00000000 ?!
b00000000 @!
b00000000 A!
b00000 B!
b00000 C!
0D!
b00000000 E!
1F!
b00000000 G!
b00000000 H!
b00000000 I!
b00000000 J!
b00000000 K!
b00000000 L!
b00000000 M!
b00000000 N!
b00000000 O!
b00000000 P!
b00000000 Q!
b00000000 R!
b00000000 S!
b00000000 T!
b00000000 U!
b00000000 V!
b00000 W!
b00000 X!
b00000000000000000000000000000000 Y!
b0000000000000000 Z!
b00000000000000000000000000000000 [!
0\!
b00000000 ]!
1^!
b00000000 _!
b00000000 `!
b00000000 a!
b00000000 b!
b00000000 c!
b00000000 d!
b00000000 e!
b00000000 f!
b00000000 g!
b00000000 h!
b00000000 i!
b00000000 j!
b00000000 k!
b00000000 l!
b00000000 m!
b00000000 n!
b00000 o!
b00000 p!
0q!
b00000000 r!
1s!
b00000000 t!
b00000000 u!
b00000000 v!
b00000000 w!
b00000000 x!
b00000000 y!
b00000000 z!
b00000000 {!
b00000000 |!
b00000000 }!
b00000000 ~!
b00000000 !"
b00000000 ""
b00000000 #"
b00000000 $"
b00000000 %"
b00000 &"
b00000 '"
b00000000000000000000000000000000 ("
b0000000000000000 )"
b00000000000000000000000000000000 *"
0+"
0,"
1-"
1."
0/"
10"
b00000000000000000000000000000000 1"
b00000000000000000000000000000000 2"
03"
b00000000000000000000000000000000000000000000000000000000000000000000000000000000000000000000000000000000000000000000000000000000 4"
08"
09"
b00000000 :"
b00000000 ;"
b00000000 <"
b00000000 ="
b00000000 >"
b00000000 ?"
b00000000 @"
b00000000 A"
b00000000000000000000000000000100 B"
b00000000000000000000000000001000 C"
b00000000000000000000000000100000 D"
b00000000000000000000000000010000 E"
b01111111111111111111111111111111 F"
b10000000000000000000000000000000 G"
#1
1+"
#2
0+"
1,"
0-"
#3
1+"
#4
0+"
1/"
b11011000000011011001001110011101 1"
b00011110100111011000100110001110 2"
19"
b10011101 :"
b10001110 ;"
b10010011 <"
b10001001 ="
b00001101 >"
b10011101 ?"
b11011000 @"
b00011110 A"
#5
b0000 #
1%
05
b10011101 6
b00001 F
0J
b10001110 K
b00001 [
0b
b10010011 c
b00001 s
0w
b10001001 x
b00001 *!
01!
b00001101 2!
b00001 B!
0F!
b10011101 G!
b00001 W!
0^!
b11011000 _!
b00001 o!
0s!
b00011110 t!
b00001 &"
1+"
18"
#6
0+"
b10000010011100001110101011110011 1"
b00110100011001101011010000100001 2"
b11110011 :"
b00100001 ;"
b11101010 <"
b10110100 ="
b01110000 >"
b01100110 ?"
b10000010 @"
b00110100 A"
#7
b10011101 &
b10010011 '
b00001101 (
b11011000 )
b10001110 *
b10001001 +
b10011101 ,
b00011110 -
b001 2
b10011101 4
b11110011 7
b00010 F
b00001 G
b10001110 I
b00100001 L
b00010 [
b00001 \
b10010011 a
b11101010 d
b00010 s
b00001 t
b10001001 v
b10110100 y
b00010 *!
b00001 +!
b00001101 0!
b01110000 3!
b00010 B!
b00001 C!
b10011101 E!
b01100110 H!
b00010 W!
b00001 X!
b11011000 ]!
b10000010 `!
b00010 o!
b00001 p!
b00011110 r!
b00110100 u!
b00010 &"
b00001 '"
1+"
#8
0+"
b10011011000010001011110000000011 1"
b10111110101110010001110010010111 2"
b00000011 :"
b10010111 ;"
b10111100 <"
b00011100 ="
b00001000 >"
b10111001 ?"
b10011011 @"
b10111110 A"
#9
b11110011 &
b11101010 '
b01110000 (
b10000010 )
b00100001 *
b10110100 +
b01100110 ,
b00110100 -
b011 2
b11110011 4
b00000011 8
b00011 F
b00010 G
b00100001 I
b10010111 M
b00011 [
b00010 \
b0010110000010110 ^
b00000000000000000010110000010110 _
b11101010 a
b10111100 e
b00011 s
b00010 t
b10110100 v
b00011100 z
b00011 *!
b00010 +!
b0011001010101011 -!
b00000000000000000011001010101011 .!
b01110000 0!
b00001000 4!
b00011 B!
b00010 C!
b01100110 E!
b10111001 I!
b00011 W!
b00010 X!
b1111101011111001 Z!
b11111111111111111111101011111001 [!
b10000010 ]!
b10011011 a!
b00011 o!
b00010 p!
b00110100 r!
b10111110 v!
b00011 &"
b00010 '"
b1111101101010000 )"
b11111111111111111111101101010000 *"
1+"
#10
0+"
b11001001111110101001111001100110 1"
b11011100101011100100001011001100 2"
b01100110 :"
b11001100 ;"
b10011110 <"
b01000010 ="
b11111010 >"
b10101110 ?"
b11001001 @"
b11011100 A"
#11
b00000011 &
b10111100 '
b00001000 (
b10011011 )
b10010111 *
b00011100 +
b10111001 ,
b10111110 -
b00000000000000000010110000010110 .
b00000000000000000011001010101011 /
b11111111111111111111101011111001 0
b11111111111111111111101101010000 1
b00000011 4
b01100110 9
b00100 F
b00011 G
b10010111 I
b11001100 N
b00100 [
b00011 \
b00000000000000000010110000010110 ]
b1111111001010011 ^
b00000000000000000010101001101001 _
b10111100 a
b10011110 f
b00100 s
b00011 t
b00011100 v
b01000010 {
b00100 *!
b00011 +!
b00000000000000000011001010101011 ,!
b0000011010001000 -!
b00000000000000000011100100110011 .!
b00001000 0!
b11111010 5!
b00100 B!
b00011 C!
b10111001 E!
b10101110 J!
b00100 W!
b00011 X!
b11111111111111111111101011111001 Y!
b0010110010100000 Z!
b00000000000000000010011110011001 [!
b10011011 ]!
b11001001 b!
b00100 o!
b00011 p!
b10111110 r!
b11011100 w!
b00100 &"
b00011 '"
b11111111111111111111101101010000 ("
b1110011001101000 )"
b11111111111111111110000110111000 *"
1+"
b11111111111111111111101101010000111111111111111111111010111110010000000000000000001100101010101100000000000000000010110000010110 4"
#12
0+"
b11000100001000010111101111001110 1"
b10111000110111000111001110101100 2"
b11001110 :"
b10101100 ;"
b01111011 <"
b01110011 ="
b00100001 >"
b11011100 ?"
b11000100 @"
b10111000 A"
